reachy_mini_rust_kinematics-1.0.2.dist-info/METADATA
reachy_mini_rust_kinematics-1.0.2.dist-info/WHEEL
reachy_mini_rust_kinematics.libs/libgcc_s-0366c7ba.so.1
reachy_mini_rust_kinematics/__init__.py
reachy_mini_rust_kinematics/__init__.pyi
reachy_mini_rust_kinematics/py.typed
reachy_mini_rust_kinematics/reachy_mini_rust_kinematics.cpython-39-arm-linux-gnueabihf.so
reachy_mini_rust_kinematics-1.0.2.dist-info/RECORD
