Metadata-Version: 2.4
Name: reachy_mini_rust_kinematics
Version: 1.0.2
Classifier: Programming Language :: Rust
Classifier: Programming Language :: Python :: Implementation :: CPython
Classifier: Programming Language :: Python :: Implementation :: PyPy
Requires-Dist: pytest ; extra == 'tests'
Provides-Extra: tests
Requires-Python: >=3.8
